mmodel/__init__.py
mmodel/draw.py
mmodel/filter.py
mmodel/graph.py
mmodel/handler.py
mmodel/metadata.py
mmodel/model.py
mmodel/modifier.py
mmodel/parser.py
mmodel/shortcut.py
mmodel/utility.py
mmodel-0.6.2.dist-info/LICENSE
mmodel-0.6.2.dist-info/METADATA
mmodel-0.6.2.dist-info/WHEEL
mmodel-0.6.2.dist-info/RECORD
