Metadata-Version: 2.1
Name: mmodel
Version: 0.6.2
Summary: Modular modeling framework for scientific modeling and prototyping.
Home-page: https://peterhs73.github.io/mmodel-docs/
License: BSD-3-Clause
Keywords: python,scientific-modeling,prototyping
Author: Peter Sun
Author-email: hs859@cornell.edu
Maintainer: Peter Sun
Maintainer-email: hs859@cornell.edu
Requires-Python: >=3.8
Classifier: Development Status :: 4 - Beta
Classifier: Intended Audience :: Developers
Classifier: License :: OSI Approved :: BSD License
Classifier: Programming Language :: Python :: 3
Classifier: Programming Language :: Python :: 3.8
Classifier: Programming Language :: Python :: 3.9
Classifier: Programming Language :: Python :: 3.10
Classifier: Programming Language :: Python :: 3.11
Classifier: Topic :: Scientific/Engineering
Classifier: Topic :: Software Development :: Libraries :: Python Modules
Provides-Extra: docs
Provides-Extra: test
Requires-Dist: graphviz (>=0.16)
Requires-Dist: h5py (>=3.6.0)
Requires-Dist: nbsphinx (==0.9.1) ; extra == "docs"
Requires-Dist: networkx (>=2.8.3)
Requires-Dist: pydata-sphinx-theme (==0.13.1) ; extra == "docs"
Requires-Dist: pytest (>=7.1.1) ; extra == "test"
Requires-Dist: pytest-cov (>=3.0.0) ; extra == "test"
Requires-Dist: sphinx (>=6.1.3,<7.0.0) ; extra == "docs"
Requires-Dist: sphinx-book-theme (==1.0.0) ; extra == "docs"
Requires-Dist: tox (>=3.24.5)
Requires-Dist: tox-conda (>=0.9.2)
Project-URL: Documentation, https://peterhs73.github.io/mmodel-docs/
Project-URL: Repository, https://github.com/peterhs73/MModel
